Metadata-Version: 2.1
Name: elasticsearch-fulltrack
Version: 0.1
Summary: Elasticsearch Fulltrack Library
Author: Ajitesh Mishra
Author-email: ajitesh.mishra@anchanto.com
